revoxx/__init__.py
revoxx/__main__.py
revoxx/app.py
revoxx/constants.py
revoxx/audio/__init__.py
revoxx/audio/audio_buffer.py
revoxx/audio/audio_queue_processor.py
revoxx/audio/buffer_manager.py
revoxx/audio/level_calculator.py
revoxx/audio/player.py
revoxx/audio/queue_manager.py
revoxx/audio/recorder.py
revoxx/audio/shared_state.py
revoxx/audio/processors/__init__.py
revoxx/audio/processors/clipping_detector.py
revoxx/audio/processors/mel_spectrogram.py
revoxx/audio/processors/processor_base.py
revoxx/controllers/__init__.py
revoxx/controllers/audio_controller.py
revoxx/controllers/device_controller.py
revoxx/controllers/dialog_controller.py
revoxx/controllers/display_controller.py
revoxx/controllers/file_operations_controller.py
revoxx/controllers/navigation_controller.py
revoxx/controllers/process_manager.py
revoxx/controllers/session_controller.py
revoxx/dataset/__init__.py
revoxx/dataset/exporter.py
revoxx/doc/USER_GUIDE.md
revoxx/resources/keyboard_shortcuts.txt
revoxx/resources/microphone.png
revoxx/resources/templates/dataset_readme.txt
revoxx/resources/templates/index_format_with_intensity.txt
revoxx/resources/templates/index_format_without_intensity.txt
revoxx/session/__init__.py
revoxx/session/inspector.py
revoxx/session/manager.py
revoxx/session/models.py
revoxx/session/script_parser.py
revoxx/ui/__init__.py
revoxx/ui/emotion_indicator.py
revoxx/ui/font_manager.py
revoxx/ui/frequency_axis.py
revoxx/ui/icon.py
revoxx/ui/info_overlay.py
revoxx/ui/recording_display_state.py
revoxx/ui/style_config.py
revoxx/ui/themes.py
revoxx/ui/widget_initializer.py
revoxx/ui/window_base.py
revoxx/ui/window_factory.py
revoxx/ui/window_manager.py
revoxx/ui/dialogs/__init__.py
revoxx/ui/dialogs/dataset_dialog.py
revoxx/ui/dialogs/dialog_utils.py
revoxx/ui/dialogs/find_dialog.py
revoxx/ui/dialogs/help_dialog.py
revoxx/ui/dialogs/import_text_dialog.py
revoxx/ui/dialogs/new_session_dialog.py
revoxx/ui/dialogs/open_session_dialog.py
revoxx/ui/dialogs/progress_dialog.py
revoxx-1.0.2.dist-info/licenses/LICENSE
revoxx-1.0.2.dist-info/METADATA
revoxx-1.0.2.dist-info/WHEEL
revoxx-1.0.2.dist-info/entry_points.txt
revoxx-1.0.2.dist-info/top_level.txt
revoxx-1.0.2.dist-info/RECORD
