Metadata-Version: 2.4
Name: revoxx
Version: 1.0.2
Summary: Speech recording application for creating high-quality speech datasets
Author-email: Grammatek ehf <info@grammatek.com>
Maintainer-email: Grammatek ehf <info@grammatek.com>
License-Expression: Apache-2.0
Project-URL: Homepage, https://github.com/icelandic-lt/revoxx
Project-URL: Documentation, https://github.com/icelandic-lt/revoxx#readme
Project-URL: Repository, https://github.com/icelandic-lt/revoxx
Project-URL: Issues, https://github.com/icelandic-lt/revoxx/issues
Keywords: speech,recording,tts,dataset,audio,voice,emotional-speech
Classifier: Development Status :: 5 - Production/Stable
Classifier: Intended Audience :: Science/Research
Classifier: Intended Audience :: Developers
Classifier: Operating System :: OS Independent
Classifier: Programming Language :: Python :: 3
Classifier: Programming Language :: Python :: 3.9
Classifier: Programming Language :: Python :: 3.10
Classifier: Programming Language :: Python :: 3.11
Classifier: Programming Language :: Python :: 3.12
Classifier: Programming Language :: Python :: 3.13
Classifier: Topic :: Multimedia :: Sound/Audio :: Capture/Recording
Classifier: Topic :: Multimedia :: Sound/Audio :: Speech
Classifier: Topic :: Scientific/Engineering :: Artificial Intelligence
Requires-Python: >=3.9
License-File: LICENSE
Requires-Dist: numpy>=2.0.2
Requires-Dist: matplotlib>=3.8.0
Requires-Dist: sounddevice>=0.5.1
Requires-Dist: soundfile>=0.12.0
Requires-Dist: tqdm>=4.65.0
Requires-Dist: markdown2>2.5.1
Requires-Dist: tkinterweb>4.4.1
Provides-Extra: vad
Requires-Dist: torch>=2.0.0; extra == "vad"
Requires-Dist: silero-vad>=5.0; extra == "vad"
Requires-Dist: torchaudio<2.8.0; extra == "vad"
Provides-Extra: dev
Requires-Dist: black>=22.0.0; extra == "dev"
Requires-Dist: isort>=5.10.0; extra == "dev"
Requires-Dist: flake8>=6.0.0; extra == "dev"
Requires-Dist: pytest>=7.0.0; extra == "dev"
Requires-Dist: pytest-cov>=3.0.0; extra == "dev"
Requires-Dist: versioningit>=2.0.0; extra == "dev"
Dynamic: license-file
